setup.py
src/PyTorrent.egg-info/PKG-INFO
src/PyTorrent.egg-info/SOURCES.txt
src/PyTorrent.egg-info/dependency_links.txt
src/PyTorrent.egg-info/top_level.txt
src/pytorrent/__init__.py
src/pytorrent/client.py
src/pytorrent/connection.py
src/pytorrent/daemon.py
src/pytorrent/torrent.py