Metadata-Version: 1.0
Name: PyTorrent
Version: 0.1.1
Summary: A simple Python API to access a transmission daemon to control torrent downloading
Home-page: http://projects.open4free.org/projects/show/pytorrent
Author: Dennis Kempin
Author-email: mail@dennis-kempin.de
License: UNKNOWN
Download-URL: http://projects.open4free.org/projects/list_files/pytorrent
Platform: UNKNOWN
Classifier: Development Status :: 3 - Alpha
Classifier: Intended Audience :: Developers
Classifier: License :: OSI Approved :: MIT License
Classifier: Operating System :: MacOS
Classifier: Operating System :: Unix
Classifier: Programming Language :: Python
Classifier: Topic :: Internet
Classifier: Topic :: Software Development :: Libraries :: Python Modules
